unifi_ml2_driver/__init__.py
unifi_ml2_driver/_i18n.py
unifi_ml2_driver/config.py
unifi_ml2_driver/dns_handler.py
unifi_ml2_driver/exceptions.py
unifi_ml2_driver/locking.py
unifi_ml2_driver/tests/__init__.py
unifi_ml2_driver/tests/unit/__init__.py
unifi_ml2_driver/tests/unit/devices/__init__.py
unifi_ml2_driver/tests/unit/devices/test_utils.py
unifi_ml2_driver/tests/unit/test_advanced_features.py
unifi_ml2_driver/tests/unit/test_config.py
unifi_ml2_driver/tests/unit/test_locking.py
unifi_ml2_driver/tests/unit/test_trunk_driver.py
unifi_ml2_driver/tests/unit/test_unifi_api.py
unifi_ml2_driver/tests/unit/test_unifi_mech.py
unifi_ml2_driver/trunk_driver.py
unifi_ml2_driver/unifi_api.py
unifi_ml2_driver/unifi_mech.py
unifi_ml2_driver/utils.py
unifi_ml2_driver-1.0.9.dist-info/LICENSE
unifi_ml2_driver-1.0.9.dist-info/METADATA
unifi_ml2_driver-1.0.9.dist-info/WHEEL
unifi_ml2_driver-1.0.9.dist-info/entry_points.txt
unifi_ml2_driver-1.0.9.dist-info/RECORD
