Metadata-Version: 2.3
Name: unifi-ml2-driver
Version: 1.0.9
Summary: Unifi Modular Layer 2 (ML2) driver.
Author: appkins
Author-email: info@appkins.io
Requires-Python: >=3.12.0
Classifier: Programming Language :: Python :: 3
Classifier: Programming Language :: Python :: 3.12
Classifier: Programming Language :: Python :: 3.13
Requires-Dist: aiohttp-unifi (>=88)
Requires-Dist: etcd3gw (>=2.1.0)
Requires-Dist: eventlet (>=0.18.2)
Requires-Dist: netmiko (>=4.1.1)
Requires-Dist: neutron (>=13.0.0.0b1)
Requires-Dist: neutron-lib (>=1.18.0)
Requires-Dist: oslo-config (>=5.2.0)
Requires-Dist: oslo-i18n (>=3.15.3)
Requires-Dist: oslo-log (>=3.36.0)
Requires-Dist: oslo-utils (>=3.40.2)
Requires-Dist: stevedore (>=1.20.0)
Requires-Dist: tenacity (>=6.0.0)
Requires-Dist: tooz (>=2.5.1)
Project-URL: Documentation, https://github.com/ubiquiti-community/unifi-ml2-driver/tree/main/doc/source
Project-URL: Repository, https://github.com/ubiquiti-community/unifi-ml2-driver
